{
  "ExpressionLimit": {"Type": "First"},
  "CollapseSettings": {
    "CollapseType": "ERA",
    "EraPad": 0
  },
  "CensorWindow": {
    "StartDate": null,
    "EndDate": null
  },
  "ConceptSets": [{
    "expression": {"items": [
      {
        "isExcluded": false,
        "concept": {
          "INVALID_REASON_CAPTION": "Valid",
          "CONCEPT_ID": 435081,
          "STANDARD_CONCEPT": "S",
          "CONCEPT_CODE": "274531002",
          "VOCABULARY_ID": "SNOMED",
          "CONCEPT_NAME": "Abnormal findings diagnostic imaging heart+coronary circulat",
          "DOMAIN_ID": "Condition",
          "STANDARD_CONCEPT_CAPTION": "Standard",
          "CONCEPT_CLASS_ID": "Clinical Finding",
          "INVALID_REASON": "V"
        },
        "includeMapped": false,
        "includeDescendants": false
      },
      {
        "isExcluded": false,
        "concept": {
          "INVALID_REASON_CAPTION": "Valid",
          "CONCEPT_ID": 43020480,
          "STANDARD_CONCEPT": "S",
          "CONCEPT_CODE": "286391000119108",
          "VOCABULARY_ID": "SNOMED",
          "CONCEPT_NAME": "Acquired coronary artery fistula",
          "DOMAIN_ID": "Condition",
          "STANDARD_CONCEPT_CAPTION": "Standard",
          "CONCEPT_CLASS_ID": "Clinical Finding",
          "INVALID_REASON": "V"
        },
        "includeMapped": false,
        "includeDescendants": false
      },
      {
        "isExcluded": false,
        "concept": {
          "INVALID_REASON_CAPTION": "Valid",
          "CONCEPT_ID": 321109,
          "STANDARD_CONCEPT": "S",
          "CONCEPT_CODE": "28574005",
          "VOCABULARY_ID": "SNOMED",
          "CONCEPT_NAME": "Congenital anomaly of coronary artery",
          "DOMAIN_ID": "Condition",
          "STANDARD_CONCEPT_CAPTION": "Standard",
          "CONCEPT_CLASS_ID": "Clinical Finding",
          "INVALID_REASON": "V"
        },
        "includeMapped": false,
        "includeDescendants": false
      },
      {
        "isExcluded": false,
        "concept": {
          "INVALID_REASON_CAPTION": "Valid",
          "CONCEPT_ID": 317576,
          "STANDARD_CONCEPT": "S",
          "CONCEPT_CODE": "53741008",
          "VOCABULARY_ID": "SNOMED",
          "CONCEPT_NAME": "Coronary arteriosclerosis",
          "DOMAIN_ID": "Condition",
          "STANDARD_CONCEPT_CAPTION": "Standard",
          "CONCEPT_CLASS_ID": "Clinical Finding",
          "INVALID_REASON": "V"
        },
        "includeMapped": false,
        "includeDescendants": false
      },
      {
        "isExcluded": false,
        "concept": {
          "INVALID_REASON_CAPTION": "Invalid",
          "CONCEPT_ID": 42872402,
          "STANDARD_CONCEPT": "",
          "CONCEPT_CODE": "1641000119107",
          "VOCABULARY_ID": "SNOMED",
          "CONCEPT_NAME": "Coronary arteriosclerosis in native artery",
          "DOMAIN_ID": "Condition",
          "STANDARD_CONCEPT_CAPTION": "Unknown",
          "CONCEPT_CLASS_ID": "Clinical Finding",
          "INVALID_REASON": "U"
        },
        "includeMapped": false,
        "includeDescendants": false
      },
      {
        "isExcluded": false,
        "concept": {
          "INVALID_REASON_CAPTION": "Valid",
          "CONCEPT_ID": 42537730,
          "STANDARD_CONCEPT": "S",
          "CONCEPT_CODE": "737278006",
          "VOCABULARY_ID": "SNOMED",
          "CONCEPT_NAME": "Coronary artery graft present",
          "DOMAIN_ID": "Condition",
          "STANDARD_CONCEPT_CAPTION": "Standard",
          "CONCEPT_CLASS_ID": "Clinical Finding",
          "INVALID_REASON": "V"
        },
        "includeMapped": false,
        "includeDescendants": false
      },
      {
        "isExcluded": false,
        "concept": {
          "INVALID_REASON_CAPTION": "Valid",
          "CONCEPT_ID": 4127089,
          "STANDARD_CONCEPT": "S",
          "CONCEPT_CODE": "23687008",
          "VOCABULARY_ID": "SNOMED",
          "CONCEPT_NAME": "Coronary artery spasm",
          "DOMAIN_ID": "Condition",
          "STANDARD_CONCEPT_CAPTION": "Standard",
          "CONCEPT_CLASS_ID": "Clinical Finding",
          "INVALID_REASON": "V"
        },
        "includeMapped": false,
        "includeDescendants": false
      },
      {
        "isExcluded": false,
        "concept": {
          "INVALID_REASON_CAPTION": "Valid",
          "CONCEPT_ID": 4108215,
          "STANDARD_CONCEPT": "S",
          "CONCEPT_CODE": "194821006",
          "VOCABULARY_ID": "SNOMED",
          "CONCEPT_NAME": "Coronary thrombosis not resulting in myocardial infarction",
          "DOMAIN_ID": "Condition",
          "STANDARD_CONCEPT_CAPTION": "Standard",
          "CONCEPT_CLASS_ID": "Clinical Finding",
          "INVALID_REASON": "V"
        },
        "includeMapped": false,
        "includeDescendants": false
      }
    ]},
    "name": "chd",
    "id": 1
  }],
  "cdmVersionRange": ">=5.0.0",
  "CensoringCriteria": [],
  "QualifiedLimit": {"Type": "First"},
  "InclusionRules": [],
  "PrimaryCriteria": {
    "CriteriaList": [{"ConditionOccurrence": {
      "OccurrenceEndDate": null,
      "CorrelatedCriteria": null,
      "ConditionTypeExclude": false,
      "CodesetId": 1,
      "ProviderSpecialty": null,
      "Gender": null,
      "VisitType": null,
      "First": true,
      "OccurrenceStartDate": null,
      "ConditionType": null,
      "ConditionSourceConcept": null,
      "ConditionStatus": null,
      "StopReason": null,
      "Age": null
    }}],
    "PrimaryCriteriaLimit": {"Type": "First"},
    "ObservationWindow": {
      "PostDays": 0,
      "PriorDays": 0
    }
  }
}